kb_builder/__init__.py
kb_builder/__main__.py
kb_builder/cli.py
kb_builder/settings.py
kb_builder/bin/__init__.py
kb_builder/bin/kb_build.py
kb_builder/bin/kb_search.py
kb_builder/configs/README.md
kb_builder/configs/base.yml
kb_builder/configs/code_repositories.yml
kb_builder/configs/config_helper.py
kb_builder/configs/data_science.yml
kb_builder/configs/general_knowledge.yml
kb_builder/configs/memory.yml
kb_builder/configs/postgres-pgvector.yml
kb_builder/configs/research_papers.yml
kb_builder/configs/sqlite-faiss.yml
kb_builder/configs/technical_docs.yml
txtai_mcp_server/__init__.py
txtai_mcp_server/__main__.py
txtai_mcp_server/server.py
txtai_mcp_server/core/__init__.py
txtai_mcp_server/core/config.py
txtai_mcp_server/core/context.py
txtai_mcp_server/core/state.py
txtai_mcp_server/prompts/__init__.py
txtai_mcp_server/prompts/analysis.py
txtai_mcp_server/prompts/search.py
txtai_mcp_server/resources/__init__.py
txtai_mcp_server/resources/config.py
txtai_mcp_server/resources/models.py
txtai_mcp_server/tools/__init__.py
txtai_mcp_server/tools/causal_config.py
txtai_mcp_server/tools/graph.py
txtai_mcp_server/tools/qa.py
txtai_mcp_server/tools/retrieve.py
txtai_mcp_server/tools/search.py
txtai_mcp_server/tools/text.py
iflow_mcp_kb_mcp_server-0.3.0.dist-info/METADATA
iflow_mcp_kb_mcp_server-0.3.0.dist-info/WHEEL
iflow_mcp_kb_mcp_server-0.3.0.dist-info/entry_points.txt
iflow_mcp_kb_mcp_server-0.3.0.dist-info/licenses/LICENSE
iflow_mcp_kb_mcp_server-0.3.0.dist-info/RECORD
