Metadata-Version: 2.4
Name: iflow-mcp_kb-mcp-server
Version: 0.3.0
Summary: A Model Context Protocol (MCP) server implementation for txtai
Author-email: geeksfino <geeksfino@gmail.com>
License: MIT
License-File: LICENSE
Requires-Python: >=3.10
Requires-Dist: beautifulsoup4>=4.10.0
Requires-Dist: bitsandbytes==0.42.0
Requires-Dist: datasets
Requires-Dist: fast-langdetect>=0.3.1
Requires-Dist: httpx>=0.28.1
Requires-Dist: markdown>=3.3.0
Requires-Dist: matplotlib>=3.5.0
Requires-Dist: mcp[cli]
Requires-Dist: networkx>=2.8.0
Requires-Dist: pandas>=1.3.0
Requires-Dist: pydantic-settings>=2.0
Requires-Dist: pypdf2>=2.0.0
Requires-Dist: python-docx>=0.8.11
Requires-Dist: python-louvain>=0.16.0
Requires-Dist: sentence-transformers>=2.2.0
Requires-Dist: torch>=2.0.0
Requires-Dist: transformers==4.49.0
Requires-Dist: trio
Requires-Dist: txtai[all,graph,pipeline]>=8.3.1
Provides-Extra: dev
Requires-Dist: black; extra == 'dev'
Requires-Dist: isort; extra == 'dev'
Requires-Dist: mypy; extra == 'dev'
Requires-Dist: pytest-asyncio; extra == 'dev'
Requires-Dist: pytest-cov; extra == 'dev'
Requires-Dist: pytest>=7.0; extra == 'dev'
